{
  "themes": {
    "light": {
      "colors": {
        "default": {
          "50": "#fafafa",
          "100": "#f2f2f3",
          "200": "#ebebec",
          "300": "#e3e3e6",
          "400": "#dcdcdf",
          "500": "#d4d4d8",
          "600": "#afafb2",
          "700": "#8a8a8c",
          "800": "#656567",
          "900": "#404041",
          "foreground": "#000",
          "DEFAULT": "#d4d4d8"
        },
        "primary": {
          "50": "#efeaf8",
          "100": "#d8ccee",
          "200": "#c1aee4",
          "300": "#ab91db",
          "400": "#9473d1",
          "500": "#7d55c7",
          "600": "#6746a4",
          "700": "#513781",
          "800": "#3b285f",
          "900": "#261a3c",
          "foreground": "#fff",
          "DEFAULT": "#7d55c7"
        },
        "secondary": {
          "50": "#e7f6fc",
          "100": "#c5e9f7",
          "200": "#a3ddf2",
          "300": "#81d0ed",
          "400": "#5fc4e9",
          "500": "#3db7e4",
          "600": "#3297bc",
          "700": "#287794",
          "800": "#1d576c",
          "900": "#123744",
          "foreground": "#000",
          "DEFAULT": "#3db7e4"
        },
        "success": {
          "50": "#eef6df",
          "100": "#d7eab3",
          "200": "#c0dd86",
          "300": "#a9d159",
          "400": "#91c42d",
          "500": "#7ab800",
          "600": "#659800",
          "700": "#4f7800",
          "800": "#3a5700",
          "900": "#253700",
          "foreground": "#000",
          "DEFAULT": "#7ab800"
        },
        "warning": {
          "50": "#fef9e8",
          "100": "#fbf1c7",
          "200": "#f9e8a7",
          "300": "#f7e086",
          "400": "#f5d766",
          "500": "#f3cf45",
          "600": "#c8ab39",
          "700": "#9e872d",
          "800": "#736221",
          "900": "#493e15",
          "foreground": "#000",
          "DEFAULT": "#f3cf45"
        },
        "danger": {
          "50": "#f3e5e6",
          "100": "#e2c1c4",
          "200": "#d19da1",
          "300": "#c0787e",
          "400": "#af545c",
          "500": "#9e3039",
          "600": "#82282f",
          "700": "#671f25",
          "800": "#4b171b",
          "900": "#2f0e11",
          "foreground": "#fff",
          "DEFAULT": "#9e3039"
        },
        "background": "#ffffff",
        "foreground": "#000000",
        "content1": {
          "DEFAULT": "#ffffff",
          "foreground": "#000"
        },
        "content2": {
          "DEFAULT": "#f4f4f5",
          "foreground": "#000"
        },
        "content3": {
          "DEFAULT": "#e4e4e7",
          "foreground": "#000"
        },
        "content4": {
          "DEFAULT": "#d4d4d8",
          "foreground": "#000"
        },
        "focus": "#006FEE",
        "overlay": "#000000"
      }
    },
    "dark": {
      "colors": {
        "default": {
          "50": "#0d0d0e",
          "100": "#19191c",
          "200": "#26262a",
          "300": "#323238",
          "400": "#3f3f46",
          "500": "#65656b",
          "600": "#8c8c90",
          "700": "#b2b2b5",
          "800": "#d9d9da",
          "900": "#ffffff",
          "foreground": "#fff",
          "DEFAULT": "#3f3f46"
        },
        "primary": {
          "50": "#261a3c",
          "100": "#3b285f",
          "200": "#513781",
          "300": "#6746a4",
          "400": "#7d55c7",
          "500": "#9473d1",
          "600": "#ab91db",
          "700": "#c1aee4",
          "800": "#d8ccee",
          "900": "#efeaf8",
          "foreground": "#fff",
          "DEFAULT": "#7d55c7"
        },
        "secondary": {
          "50": "#123744",
          "100": "#1d576c",
          "200": "#287794",
          "300": "#3297bc",
          "400": "#3db7e4",
          "500": "#5fc4e9",
          "600": "#81d0ed",
          "700": "#a3ddf2",
          "800": "#c5e9f7",
          "900": "#e7f6fc",
          "foreground": "#000",
          "DEFAULT": "#3db7e4"
        },
        "success": {
          "50": "#253700",
          "100": "#3a5700",
          "200": "#4f7800",
          "300": "#659800",
          "400": "#7ab800",
          "500": "#91c42d",
          "600": "#a9d159",
          "700": "#c0dd86",
          "800": "#d7eab3",
          "900": "#eef6df",
          "foreground": "#000",
          "DEFAULT": "#7ab800"
        },
        "warning": {
          "50": "#493e15",
          "100": "#736221",
          "200": "#9e872d",
          "300": "#c8ab39",
          "400": "#f3cf45",
          "500": "#f5d766",
          "600": "#f7e086",
          "700": "#f9e8a7",
          "800": "#fbf1c7",
          "900": "#fef9e8",
          "foreground": "#000",
          "DEFAULT": "#f3cf45"
        },
        "danger": {
          "50": "#2f0e11",
          "100": "#4b171b",
          "200": "#671f25",
          "300": "#82282f",
          "400": "#9e3039",
          "500": "#af545c",
          "600": "#c0787e",
          "700": "#d19da1",
          "800": "#e2c1c4",
          "900": "#f3e5e6",
          "foreground": "#fff",
          "DEFAULT": "#9e3039"
        },
        "background": "#000000",
        "foreground": "#ffffff",
        "content1": {
          "DEFAULT": "#18181b",
          "foreground": "#fff"
        },
        "content2": {
          "DEFAULT": "#27272a",
          "foreground": "#fff"
        },
        "content3": {
          "DEFAULT": "#3f3f46",
          "foreground": "#fff"
        },
        "content4": {
          "DEFAULT": "#52525b",
          "foreground": "#fff"
        },
        "focus": "#006FEE",
        "overlay": "#ffffff"
      }
    }
  },
  "layout": {
    "disabledOpacity": "0.5"
  }
}
